Metadata-Version: 2.2
Name: pydn2
Version: 0.0.6
Summary: Thin wrapper around libidn2
Author-email: StupidCodeFactory <ymarquet@gmail.com>
License: MIT
Project-URL: Homepage, https://github.com/StupidCodeFactory/pydn2
Project-URL: Documentation, https://github.com/StupidCodeFactory/pydn2/blob/main/tests/test_pydn2.py
Project-URL: Repository, https://github.com/StupidCodeFactory/pydn2
Project-URL: Changelog, https://github.com/StupidCodeFactory/pydn2/releases
Keywords: libidn2,idn2,IDN2008
Requires-Python: >=3.9
